setup.py
gradio_tttt/__init__.py
gradio_tttt/add.py
gradio_tttt.egg-info/PKG-INFO
gradio_tttt.egg-info/SOURCES.txt
gradio_tttt.egg-info/dependency_links.txt
gradio_tttt.egg-info/top_level.txt