Metadata-Version: 2.1
Name: gradio_tttt
Version: 1.0.0
Summary: 测试本地发布模块
Author: zzzz
Author-email: aiteerzhao@gmail.com
